{
  "url": "https://www.climate.gov/news-features/feed/take-deeper-look-2010-2015-texas-drought-through-new-interactive-web-app",
  "title": "Take a deeper look into the 2010-2015 Texas drought through this new interactive web app",
  "date": null,
  "content": "From 2010-2015, Texas experienced a wild hydrological rollercoaster, marked with both extreme drought and wet conditions. A new NOAA web application allows users to take a deeper look into this ...\nClick to read the full article",
  "source": ""
}