{
  "url": "https://www.climate.gov/news-features/feed/noaa-us-navy-will-increase-nation%E2%80%99s-unmanned-maritime-systems-operations",
  "title": "NOAA, U.S. Navy will increase nation’s unmanned maritime systems operations",
  "date": null,
  "content": "NOAA and the United States Navy have signed a new agreement to jointly expand the development and operations of unmanned maritime systems in the nation’s coastal and world’s ocean waters. This will enable NOAA to leverage the Navy’s expertise, infrastructure, best practices and training to accelerate its science, service and stewardship mission.\nClick to read the full article",
  "source": ""
}