{
  "url": "https://www.climate.gov/news-features/feed/applications-now-being-accepted-2022-urban-heat-island-mapping-campaigns",
  "title": "Applications now being accepted for 2022 Urban Heat Island Mapping Campaigns",
  "date": null,
  "content": "<p>The urban heat island bakes Phoenix. Credit: NOAA CPO</p>\nThe urban heat island bakes Phoenix. Credit: NOAA CPO\nThe National Integrated Heat Health Information System (NIHHIS) and CAPA Strategies are now accepting applications from organizations interested in participating in the 2022 cohort of the Urban Heat Island (UHI) mapping campaigns. Over the past four years, more than three dozen cities across the United States. have participated in the UHI campaign program to map the hottest parts of their communities. Cities in 11 states participated in the 2021 campaign, which finished data collection in September. Mapping reports will be released on a rolling basis through December.\nRead more at the link below.\nClick to read the full article",
  "source": ""
}