{
  "url": "https://www.climate.gov/news-features/understanding-climate/september-2020-was-warm-and-dry-us-west-cool-middle-and-wet",
  "title": "September 2020 was warm and dry in the U.S. West, cool in the middle, and wet in the South and Southeast",
  "date": null,
  "content": "According to the latest monthly summary from NOAA National Centers for Environmental Information (NCEI), the average contiguous U.S. temperature in September 2020 was 66.0°F, 1.1°F above the 20th-century average, ranking in the warmest one-third of the 126-year period of record. For the year-to-date, the contiguous U.S. temperature was 57.3°F, 2.3°F above the 20th-century average, ranking sixth warmest in the January-September record.\nTemperatures across the contiguous United States in September 2020 compared ot the 1981-2010 average. Map from Data Snapshots on Climate.gov.\nHighlights for temperature included:\nMeanwhile, the September precipitation total for the contiguous U.S. was 2.38 inches, 0.11 inch below average, ranking in the middle one-third of the 126-year period of record. For the year-to-date, the national precipitation total was 24.08 inches, 0.88 inch above average, also ranking in the middle one-third of the January-September record.\nU.S. precipitation as a percent of the 1981-2010 average in September 2020. Map from Data Snapshots on Climate.gov.\nHighlights for precipitation included:\nFor more details, including a summary of the number of billion-dollar disasters that have occurred so far in 2020, read the NCEI's full September 2020 climate summary.\nHelp us improve our content",
  "source": "climate.gov"
}